lithic/__init__.py
lithic/_base_client.py
lithic/_client.py
lithic/_compat.py
lithic/_constants.py
lithic/_exceptions.py
lithic/_files.py
lithic/_legacy_response.py
lithic/_models.py
lithic/_qs.py
lithic/_resource.py
lithic/_response.py
lithic/_streaming.py
lithic/_types.py
lithic/_version.py
lithic/pagination.py
lithic/py.typed
lithic/_utils/__init__.py
lithic/_utils/_compat.py
lithic/_utils/_datetime_parse.py
lithic/_utils/_logs.py
lithic/_utils/_proxy.py
lithic/_utils/_reflection.py
lithic/_utils/_resources_proxy.py
lithic/_utils/_streams.py
lithic/_utils/_sync.py
lithic/_utils/_transform.py
lithic/_utils/_typing.py
lithic/_utils/_utils.py
lithic/lib/.keep
lithic/resources/__init__.py
lithic/resources/account_activity.py
lithic/resources/account_holders.py
lithic/resources/accounts.py
lithic/resources/auth_stream_enrollment.py
lithic/resources/balances.py
lithic/resources/book_transfers.py
lithic/resources/card_bulk_orders.py
lithic/resources/card_programs.py
lithic/resources/digital_card_art.py
lithic/resources/disputes.py
lithic/resources/disputes_v2.py
lithic/resources/external_payments.py
lithic/resources/funding_events.py
lithic/resources/management_operations.py
lithic/resources/network_programs.py
lithic/resources/payments.py
lithic/resources/responder_endpoints.py
lithic/resources/tokenization_decisioning.py
lithic/resources/tokenizations.py
lithic/resources/transfer_limits.py
lithic/resources/webhooks.py
lithic/resources/auth_rules/__init__.py
lithic/resources/auth_rules/auth_rules.py
lithic/resources/auth_rules/v2/__init__.py
lithic/resources/auth_rules/v2/backtests.py
lithic/resources/auth_rules/v2/v2.py
lithic/resources/cards/__init__.py
lithic/resources/cards/balances.py
lithic/resources/cards/cards.py
lithic/resources/cards/financial_transactions.py
lithic/resources/credit_products/__init__.py
lithic/resources/credit_products/credit_products.py
lithic/resources/credit_products/extended_credit.py
lithic/resources/credit_products/prime_rates.py
lithic-0.113.0.dist-info/METADATA
lithic-0.113.0.dist-info/WHEEL
lithic-0.113.0.dist-info/licenses/LICENSE
lithic-0.113.0.dist-info/RECORD
